MANIFEST.in
README.rst
setup.cfg
setup.py
requests_proxy/__init__.py
requests_proxy/tests.py
requests_proxy.egg-info/PKG-INFO
requests_proxy.egg-info/SOURCES.txt
requests_proxy.egg-info/dependency_links.txt
requests_proxy.egg-info/entry_points.txt
requests_proxy.egg-info/not-zip-safe
requests_proxy.egg-info/requires.txt
requests_proxy.egg-info/top_level.txt