Metadata-Version: 1.0
Name: requests-proxy
Version: 0.1
Summary: A WSGI Proxy using requests
Home-page: https://github.com/gawel/requests_proxy
Author: Gael Pasgrimaud
Author-email: gael@gawel.org
License: Copyright 2012 Gael Pasgrimaud
